LICENSE
MANIFEST.in
README.md
gca_setup.py
requirements.txt
setup.py
gcadev.egg-info/PKG-INFO
gcadev.egg-info/SOURCES.txt
gcadev.egg-info/dependency_links.txt
gcadev.egg-info/entry_points.txt
gcadev.egg-info/not-zip-safe
gcadev.egg-info/requires.txt
gcadev.egg-info/top_level.txt
gpt_computer_assistant/__init__.py
gpt_computer_assistant/agentic.py
gpt_computer_assistant/api.py
gpt_computer_assistant/character.py
gpt_computer_assistant/classes.py
gpt_computer_assistant/custom_callback.py
gpt_computer_assistant/display_tools.py
gpt_computer_assistant/gpt_computer_assistant.py
gpt_computer_assistant/llm.py
gpt_computer_assistant/llm_settings.py
gpt_computer_assistant/remote.py
gpt_computer_assistant/standard_tools.py
gpt_computer_assistant/start.py
gpt_computer_assistant/teams.py
gpt_computer_assistant/tooler.py
gpt_computer_assistant/top_bar_wrapper.py
gpt_computer_assistant/tracing.py
gpt_computer_assistant/version.py
gpt_computer_assistant/agent/__init__.py
gpt_computer_assistant/agent/agent.py
gpt_computer_assistant/agent/agent_tools.py
gpt_computer_assistant/agent/assistant.py
gpt_computer_assistant/agent/background.py
gpt_computer_assistant/agent/chat_history.py
gpt_computer_assistant/agent/process.py
gpt_computer_assistant/audio/__init__.py
gpt_computer_assistant/audio/input_box.py
gpt_computer_assistant/audio/record.py
gpt_computer_assistant/audio/stt.py
gpt_computer_assistant/audio/tts.py
gpt_computer_assistant/audio/wake_word.py
gpt_computer_assistant/audio/stt_providers/openai.py
gpt_computer_assistant/audio/stt_providers/openai_whisper_local.py
gpt_computer_assistant/audio/tts_providers/microsoft_local.py
gpt_computer_assistant/audio/tts_providers/openai.py
gpt_computer_assistant/cu/ask_anthropic.py
gpt_computer_assistant/cu/base.py
gpt_computer_assistant/cu/computer.py
gpt_computer_assistant/cu/run.py
gpt_computer_assistant/gui/__init__.py
gpt_computer_assistant/gui/button.py
gpt_computer_assistant/gui/llmsettings.py
gpt_computer_assistant/gui/settings.py
gpt_computer_assistant/gui/signal.py
gpt_computer_assistant/mcp/tool.py
gpt_computer_assistant/screen/__init__.py
gpt_computer_assistant/screen/shot.py
gpt_computer_assistant/utils/chat_history.py
